cfg_analysis_tool_py/__init__.py
cfg_analysis_tool_py/analyzer.py
cfg_analysis_tool_py/cfg.py
cfg_analysis_tool_py/cfg_builder.py
cfg_analysis_tool_py/path.py
cfg_analysis_tool_py-0.1.0.dist-info/LICENSE.txt
cfg_analysis_tool_py-0.1.0.dist-info/METADATA
cfg_analysis_tool_py-0.1.0.dist-info/WHEEL
cfg_analysis_tool_py-0.1.0.dist-info/top_level.txt
cfg_analysis_tool_py-0.1.0.dist-info/RECORD
