Metadata-Version: 2.1
Name: cfg_analysis_tool_py
Version: 0.1.0
Summary: CFG Analysis Tool
Author: group 6
License-File: LICENSE.txt
Requires-Dist: aiohttp==3.9.1
Requires-Dist: aiosignal==1.3.1
Requires-Dist: anyio==4.1.0
Requires-Dist: attrs==23.1.0
Requires-Dist: certifi==2023.11.17
Requires-Dist: cfgv==3.4.0
Requires-Dist: charset-normalizer==3.3.2
Requires-Dist: click==8.1.7
Requires-Dist: contourpy==1.2.0
Requires-Dist: coverage==7.3.3
Requires-Dist: cycler==0.12.1
Requires-Dist: datasets==2.14.7
Requires-Dist: dill==0.3.7
Requires-Dist: distlib==0.3.8
Requires-Dist: fastapi==0.97.0
Requires-Dist: filelock==3.13.1
Requires-Dist: fonttools==4.46.0
Requires-Dist: frozenlist==1.4.0
Requires-Dist: fsspec==2023.10.0
Requires-Dist: h11==0.14.0
Requires-Dist: huggingface-hub==0.19.4
Requires-Dist: identify==2.5.33
Requires-Dist: idna==3.6
Requires-Dist: kiwisolver==1.4.5
Requires-Dist: matplotlib==3.8.0
Requires-Dist: multidict==6.0.4
Requires-Dist: multiprocess==0.70.15
Requires-Dist: networkx==3.1
Requires-Dist: nodeenv==1.8.0
Requires-Dist: numpy==1.26.2
Requires-Dist: packaging==23.2
Requires-Dist: pandas==2.1.4
Requires-Dist: Pillow==10.1.0
Requires-Dist: platformdirs==4.1.0
Requires-Dist: pre-commit==3.4.0
Requires-Dist: pyarrow==14.0.1
Requires-Dist: pyarrow-hotfix==0.6
Requires-Dist: pydantic==1.10.13
Requires-Dist: pygraphviz==1.11
Requires-Dist: pyparsing==3.1.1
Requires-Dist: python-dateutil==2.8.2
Requires-Dist: pytz==2023.3.post1
Requires-Dist: PyYAML==6.0.1
Requires-Dist: requests==2.31.0
Requires-Dist: six==1.16.0
Requires-Dist: sniffio==1.3.0
Requires-Dist: starlette==0.27.0
Requires-Dist: tqdm==4.66.1
Requires-Dist: tree-sitter==0.23.2
Requires-Dist: tree-sitter-python==0.23.5
Requires-Dist: typing_extensions==4.9.0
Requires-Dist: tzdata==2023.3
Requires-Dist: urllib3==2.1.0
Requires-Dist: uvicorn==0.22.0
Requires-Dist: virtualenv==20.25.0
Requires-Dist: xxhash==3.4.1
Requires-Dist: yarl==1.9.4
